odoo/addons/l10n_es_aeat_mod349_extra_data/README.rst
odoo/addons/l10n_es_aeat_mod349_extra_data/__init__.py
odoo/addons/l10n_es_aeat_mod349_extra_data/__manifest__.py
odoo/addons/l10n_es_aeat_mod349_extra_data/data/aeat_349_map_data.xml
odoo/addons/l10n_es_aeat_mod349_extra_data/i18n/l10n_es_aeat_mod349_extra_data.pot
odoo/addons/l10n_es_aeat_mod349_extra_data/readme/CONTRIBUTORS.rst
odoo/addons/l10n_es_aeat_mod349_extra_data/readme/DESCRIPTION.rst
odoo/addons/l10n_es_aeat_mod349_extra_data/readme/HISTORY.rst
odoo/addons/l10n_es_aeat_mod349_extra_data/static/description/icon.png
odoo/addons/l10n_es_aeat_mod349_extra_data/static/description/index.html
odoo11_addon_l10n_es_aeat_mod349_extra_data-11.0.1.0.0.99.dev3.dist-info/METADATA
odoo11_addon_l10n_es_aeat_mod349_extra_data-11.0.1.0.0.99.dev3.dist-info/WHEEL
odoo11_addon_l10n_es_aeat_mod349_extra_data-11.0.1.0.0.99.dev3.dist-info/top_level.txt
odoo11_addon_l10n_es_aeat_mod349_extra_data-11.0.1.0.0.99.dev3.dist-info/RECORD
